singular_client/__init__.py
singular_client/_bases.py
singular_client/api.py
singular_client/documents.py
singular_client/models.py
singular_client/utils.py
singular_client/endpoints/__init__.py
singular_client/endpoints/governance.py
singular_client/endpoints/links.py
singular_client/endpoints/links_legacy.py
singular_client/endpoints/monetization.py
singular_client/endpoints/reporting.py
singular_client/endpoints/skan.py
singular_client-0.1.8.dist-info/METADATA
singular_client-0.1.8.dist-info/WHEEL
singular_client-0.1.8.dist-info/licenses/LICENSE
singular_client-0.1.8.dist-info/RECORD
