Metadata-Version: 2.1
Name: singular-client
Version: 0.1.8
Summary: A modern Singular API client.
Author-email: Ryan Young <dev@ryayoung.com>
License-Expression: MIT
License-File: LICENSE
Classifier: Development Status :: 3 - Alpha
Classifier: Intended Audience :: Developers
Classifier: License :: OSI Approved :: MIT License
Classifier: Operating System :: OS Independent
Classifier: Programming Language :: Python :: 3.11
Classifier: Topic :: Software Development :: Libraries
Requires-Dist: requests
